{"summaries":[{"symbol":{"__symbol":0,"members":[]},"metadata":{"__symbolic":"class","members":{"rating":[{"__symbolic":"property","decorators":[{"__symbolic":"call","expression":{"__symbol":1,"members":[]}}]}],"increase":[{"__symbolic":"property","decorators":[{"__symbolic":"call","expression":{"__symbol":2,"members":[]}}]}],"decrease":[{"__symbolic":"property","decorators":[{"__symbolic":"call","expression":{"__symbol":2,"members":[]}}]}],"raiseIncrease":[{"__symbolic":"method"}],"raiseDecrease":[{"__symbolic":"method"}]}},"type":{"summaryKind":1,"type":{"reference":{"__symbol":0,"members":[]},"diDeps":[],"lifecycleHooks":[]},"isComponent":true,"selector":"tr-rating-button","exportAs":null,"inputs":{"rating":"rating"},"outputs":{"increase":"increase","decrease":"decrease"},"hostListeners":{},"hostProperties":{},"hostAttributes":{},"providers":[],"viewProviders":[],"queries":[],"viewQueries":[],"entryComponents":[],"changeDetection":1,"template":{"animations":[],"ngContentSelectors":[],"encapsulation":0},"componentViewType":{"__symbol":3,"members":[]},"rendererType":{"__symbol":4,"members":[]},"componentFactory":{"__symbol":5,"members":[]}}}],"symbols":[{"__symbol":0,"name":"RatingButtonComponent","filePath":"C:/workbench/trainings/angular/ng-pwa/src/app/book/rating-button/rating-button.component.d.ts"},{"__symbol":1,"name":"Input","filePath":"C:/workbench/trainings/angular/ng-pwa/node_modules/@angular/core/core.d.ts"},{"__symbol":2,"name":"Output","filePath":"C:/workbench/trainings/angular/ng-pwa/node_modules/@angular/core/core.d.ts"},{"__symbol":3,"name":"View_RatingButtonComponent_0","filePath":"C:/workbench/trainings/angular/ng-pwa/src/app/book/rating-button/rating-button.component.ngfactory.d.ts"},{"__symbol":4,"name":"RenderType_RatingButtonComponent","filePath":"C:/workbench/trainings/angular/ng-pwa/src/app/book/rating-button/rating-button.component.ngfactory.d.ts"},{"__symbol":5,"name":"RatingButtonComponentNgFactory","filePath":"C:/workbench/trainings/angular/ng-pwa/src/app/book/rating-button/rating-button.component.ngfactory.d.ts"}]}